ollanet/__init__.py
ollanet/api.py
ollanet/cli.py
ollanet/ngrok_handler.py
ollanet/utils.py
ollanet-0.1.0.dist-info/LICENSE
ollanet-0.1.0.dist-info/METADATA
ollanet-0.1.0.dist-info/WHEEL
ollanet-0.1.0.dist-info/entry_points.txt
ollanet-0.1.0.dist-info/top_level.txt
ollanet-0.1.0.dist-info/RECORD
