Metadata-Version: 2.1
Name: ollanet
Version: 0.1.0
Summary: A CLI tool for Ollama API with ngrok tunneling
Author: Your Name
Author-email: your.email@example.com
License-File: LICENSE
Requires-Dist: fastapi
Requires-Dist: uvicorn
Requires-Dist: pyngrok
Requires-Dist: simple-term-menu
Requires-Dist: requests
Requires-Dist: pydantic
Requires-Dist: click
